skill_ovos_spelling/LICENSE
skill_ovos_spelling/README.md
skill_ovos_spelling/__init__.py
skill_ovos_spelling/version.py
skill_ovos_spelling/locale/ca-es/Spell.voc
skill_ovos_spelling/locale/ca-es/skill.json
skill_ovos_spelling/locale/ca-es/word.rx
skill_ovos_spelling/locale/da-dk/Spell.voc
skill_ovos_spelling/locale/da-dk/skill.json
skill_ovos_spelling/locale/da-dk/word.rx
skill_ovos_spelling/locale/de-de/Spell.voc
skill_ovos_spelling/locale/de-de/skill.json
skill_ovos_spelling/locale/de-de/word.rx
skill_ovos_spelling/locale/el-gr/Spell.voc
skill_ovos_spelling/locale/el-gr/word.rx
skill_ovos_spelling/locale/en-us/Spell.voc
skill_ovos_spelling/locale/en-us/skill.json
skill_ovos_spelling/locale/en-us/word.rx
skill_ovos_spelling/locale/es-es/Spell.voc
skill_ovos_spelling/locale/es-es/word.rx
skill_ovos_spelling/locale/eu-eu/Spell.voc
skill_ovos_spelling/locale/eu-eu/word.rx
skill_ovos_spelling/locale/fa-ir/Spell.voc
skill_ovos_spelling/locale/fa-ir/word.rx
skill_ovos_spelling/locale/fr-fr/Spell.voc
skill_ovos_spelling/locale/fr-fr/word.rx
skill_ovos_spelling/locale/gl-es/Spell.voc
skill_ovos_spelling/locale/gl-es/skill.json
skill_ovos_spelling/locale/gl-es/word.rx
skill_ovos_spelling/locale/hu-hu/Spell.voc
skill_ovos_spelling/locale/hu-hu/word.rx
skill_ovos_spelling/locale/it-it/Spell.voc
skill_ovos_spelling/locale/it-it/word.rx
skill_ovos_spelling/locale/nl-nl/Spell.voc
skill_ovos_spelling/locale/nl-nl/word.rx
skill_ovos_spelling/locale/pl-pl/Spell.voc
skill_ovos_spelling/locale/pl-pl/word.rx
skill_ovos_spelling/locale/pt-br/Spell.voc
skill_ovos_spelling/locale/pt-br/word.rx
skill_ovos_spelling/locale/pt-pt/Spell.voc
skill_ovos_spelling/locale/pt-pt/word.rx
skill_ovos_spelling/locale/ro-ro/Spell.voc
skill_ovos_spelling/locale/ro-ro/word.rx
skill_ovos_spelling/locale/ru-ru/Spell.voc
skill_ovos_spelling/locale/ru-ru/word.rx
skill_ovos_spelling/locale/sv-se/Spell.voc
skill_ovos_spelling/locale/sv-se/word.rx
skill_ovos_spelling/locale/tr-tr/Spell.voc
skill_ovos_spelling/ovos_skill_spelling.egg-info/PKG-INFO
skill_ovos_spelling/ovos_skill_spelling.egg-info/SOURCES.txt
skill_ovos_spelling/ovos_skill_spelling.egg-info/dependency_links.txt
skill_ovos_spelling/ovos_skill_spelling.egg-info/entry_points.txt
skill_ovos_spelling/ovos_skill_spelling.egg-info/top_level.txt
ovos_skill_spelling-0.2.6.dist-info/LICENSE
ovos_skill_spelling-0.2.6.dist-info/METADATA
ovos_skill_spelling-0.2.6.dist-info/WHEEL
ovos_skill_spelling-0.2.6.dist-info/entry_points.txt
ovos_skill_spelling-0.2.6.dist-info/top_level.txt
ovos_skill_spelling-0.2.6.dist-info/RECORD
