Metadata-Version: 2.1
Name: ovos-skill-spelling
Version: 0.2.6
Summary: OVOS spelling skill
Home-page: https://github.com/OpenVoiceOS/skill-ovos-spelling
Author: OpenVoiceOS
Author-email: jarbasai@mailfence.com
License: Apache-2.0
Keywords: ovos skill plugin
License-File: LICENSE
